langgraph2slack/__init__.py
langgraph2slack/bot.py
langgraph2slack/config.py
langgraph2slack/transformers.py
langgraph2slack/utils.py
langgraph2slack/handlers/__init__.py
langgraph2slack/handlers/base.py
langgraph2slack/handlers/message.py
langgraph2slack/handlers/stream.py
langgraph2slack/mixins/__init__.py
langgraph2slack/mixins/reactions.py
langgraph2slack/templates/basic.py
langgraph2slack/templates/with_transformers.py
langgraph2slack-0.3.0.dist-info/METADATA
langgraph2slack-0.3.0.dist-info/WHEEL
langgraph2slack-0.3.0.dist-info/top_level.txt
langgraph2slack-0.3.0.dist-info/RECORD
