Metadata-Version: 2.4
Name: langgraph2slack
Version: 0.3.0
Summary: Simple package to connect LangGraph applications to Slack
Author-email: Siavash Yasini <siavash.yasini@gmail.com>
License: MIT
Project-URL: Homepage, https://github.com/syasini/langgraph2slack
Project-URL: Documentation, https://github.com/syasini/langgraph2slack#readme
Project-URL: Repository, https://github.com/syasini/langgraph2slack
Project-URL: Issues, https://github.com/syasini/langgraph2slack/issues
Keywords: langgraph,slack,chatbot,ai,langchain
Classifier: Development Status :: 3 - Alpha
Classifier: Intended Audience :: Developers
Classifier: License :: OSI Approved :: MIT License
Classifier: Programming Language :: Python :: 3
Classifier: Programming Language :: Python :: 3.10
Classifier: Programming Language :: Python :: 3.11
Classifier: Programming Language :: Python :: 3.12
Classifier: Topic :: Software Development :: Libraries :: Python Modules
Classifier: Topic :: Communications :: Chat
Requires-Python: >=3.10
Requires-Dist: fastapi>=0.100.0
Requires-Dist: langgraph-sdk>=0.1.0
Requires-Dist: langsmith>=0.1.0
Requires-Dist: slack-bolt>=1.18.0
Requires-Dist: aiohttp>=3.8.0
Requires-Dist: pydantic>=2.0.0
Requires-Dist: pydantic-settings>=2.0.0
Requires-Dist: python-dotenv>=1.0.0
Requires-Dist: uvicorn>=0.23.0
Provides-Extra: dev
Requires-Dist: pytest>=7.4.0; extra == "dev"
Requires-Dist: pytest-asyncio>=0.21.0; extra == "dev"
Requires-Dist: black>=23.0.0; extra == "dev"
Requires-Dist: ruff>=0.1.0; extra == "dev"
